conexionbddian/__init__.py
conexionbddian/conexionbddian.py
conexionbddian-0.0.7.dist-info/METADATA
conexionbddian-0.0.7.dist-info/WHEEL
conexionbddian-0.0.7.dist-info/top_level.txt
conexionbddian-0.0.7.dist-info/RECORD
