Metadata-Version: 2.1
Name: conexionbddian
Version: 0.0.7
Summary: Paquete conexión SOLEM para subdirección Riesgo - DIAN
Author-email: Sebastian Leon <joan2613@gmail.com>
Keywords: Base datos,solem,dian
Classifier: Development Status :: 3 - Alpha
Classifier: Intended Audience :: Education
Classifier: Programming Language :: Python :: 3
Classifier: Operating System :: MacOS :: MacOS X
Classifier: Operating System :: Microsoft :: Windows
Requires-Python: >=3.8
Requires-Dist: sqlalchemy
Requires-Dist: cx-Oracle
Requires-Dist: pandas
Requires-Dist: python-decouple
